Lemke.cp311-win_amd64.pyd
Quinn_Fernandes.cp311-win_amd64.pyd
Splines.cp311-win_amd64.pyd
eventometrics/CapacityModels.py
eventometrics/Extrapolators.py
eventometrics/Lemke.cp311-win_amd64.pyd
eventometrics/Lemke.pxd
eventometrics/Lemke.pyx
eventometrics/Metrics.py
eventometrics/Quinn_Fernandes.cp311-win_amd64.pyd
eventometrics/Quinn_Fernandes.pyx
eventometrics/Search.py
eventometrics/Splines.cp311-win_amd64.pyd
eventometrics/Splines.pyx
eventometrics/__init__.py
eventometrics/base.py
eventometrics/optimization.py
eventometrics-0.1.107.dist-info/licenses/LICENSE
eventometrics-0.1.107.dist-info/METADATA
eventometrics-0.1.107.dist-info/WHEEL
eventometrics-0.1.107.dist-info/top_level.txt
eventometrics-0.1.107.dist-info/RECORD
