Metadata-Version: 2.4
Name: eventometrics
Version: 0.1.107
Summary: A framework for forecasting economic events.
Author: Korablev Yu.A.
Author-email: "Korablev Yu.A." <yura-korablyov@yandex.ru>
License-Expression: BSD-3-Clause
Keywords: eventometrics,events,economic events,forecast,capacity model
Classifier: Programming Language :: Python :: 3
Classifier: Operating System :: OS Independent
Requires-Python: >=3.9
License-File: LICENSE
Requires-Dist: numpy~=2.3.0
Requires-Dist: Cython~=3.1.2
Requires-Dist: setuptools~=80.9.0
Requires-Dist: joblib~=1.5.1
Dynamic: author
Dynamic: license-file
